{
  "name": "Cosmic Challenges",
  "author": "Mini Golf Break Team",
  "description": "A space-themed mini golf course with various obstacles and challenges",
  "elements": [
    {
      "type": "hole",
      "id": "hole_1",
      "name": "Straight Shot",
      "index": 0,
      "position": [0, 0, 0],
      "holePosition": [0, 0, -8],
      "startPosition": [0, 0, 8],
      "courseWidth": 4,
      "courseLength": 20,
      "par": 3,
      "description": "A simple straight shot to get started",
      "hazards": []
    },
    {
      "type": "hole",
      "id": "hole_2",
      "name": "Sandy Challenge",
      "index": 1,
      "position": [20, 0, 0],
      "holePosition": [24, 0, 8],
      "startPosition": [20, 0, -8],
      "courseWidth": 6,
      "courseLength": 24,
      "par": 4,
      "description": "Dogleg right with sand traps",
      "hazards": [
        {
          "type": "sand",
          "position": [22, 0, 0],
          "size": {"x": 2, "y": 0.2, "z": 2}
        }
      ]
    },
    {
      "type": "hole",
      "id": "hole_3",
      "name": "Wall Puzzle",
      "index": 2,
      "position": [40, 0, 0],
      "holePosition": [40, 0, 8],
      "startPosition": [40, 0, -8],
      "courseWidth": 5,
      "courseLength": 22,
      "par": 4,
      "description": "Navigate through a maze of walls",
      "hazards": []
    },
    {
      "type": "bunker",
      "id": "bunker_1",
      "name": "Center Bunker",
      "position": [40, 0, 0],
      "radius": 1.5,
      "depth": 0.3,
      "sandColor": "0xE6C388"
    },
    {
      "type": "wall",
      "id": "wall_1",
      "name": "Obstacle Wall 1",
      "position": [40, 0, -3],
      "width": 2,
      "height": 0.8,
      "depth": 0.2,
      "rotation": 0.7853981634,
      "color": "0xA0522D",
      "wallType": "wood",
      "restitution": 0.6
    },
    {
      "type": "wall",
      "id": "wall_2",
      "name": "Obstacle Wall 2",
      "position": [40, 0, 3],
      "width": 2,
      "height": 0.8,
      "depth": 0.2,
      "rotation": -0.7853981634,
      "color": "0x8B4513",
      "wallType": "stone",
      "restitution": 0.3
    },
    {
      "type": "bunker",
      "id": "bunker_2",
      "name": "Dogleg Bunker",
      "position": [22, 0, 4],
      "radius": 1.8,
      "depth": 0.4,
      "sandColor": "0xDEB887"
    }
  ]
} 